LICENSE
sdf_heroku_deploy/__init__.py
sdf_heroku_deploy/sdfh_cli.py
sdf_heroku_deploy/simple_df_deploy.py
sdf_heroku_deploy-2.0.0.dist-info/entry_points.txt
sdf_heroku_deploy-2.0.0.dist-info/LICENSE
sdf_heroku_deploy-2.0.0.dist-info/WHEEL
sdf_heroku_deploy-2.0.0.dist-info/METADATA
sdf_heroku_deploy-2.0.0.dist-info/RECORD
