Metadata-Version: 2.1
Name: sdf-heroku-deploy
Version: 2.0.0
Summary: This script generates a Dockerfile with the basic settings to deploy your flask application to heroku. And as a bonus a steps.txt with the step by step for you to publish the project.
Home-page: https://github.com/darkmathew/simple-docker-flask-deploy-to-heroku
License: MIT
Author: Matheus Santos
Author-email: 78329418+darkmathew@users.noreply.github.com
Requires-Python: >=3.10,<4.0
Classifier: License :: OSI Approved :: MIT License
Classifier: Programming Language :: Python :: 3
Classifier: Programming Language :: Python :: 3.10
Project-URL: Repository, https://github.com/darkmathew/simple-docker-flask-deploy-to-heroku
